[
  {
    "name": "Financial Education",
    "handle": "FinancialEducation",
    "channel_id": "UCCmJVw9xQfYuuAAwZGedKRg"
  },
  {
    "name": "Everything Money",
    "handle": "EverythingMoney",
    "channel_id": "UCJm2RBjxfvdTdtJcYtFx2Xw"
  },
  {
    "name": "Sven Carlin",
    "handle": "Value-Investing",
    "channel_id": "UCrTTBSUr0zhPU56UQljag5A"
  },
  {
    "name": "Brian Stoffel",
    "handle": "brianstoffelyt",
    "channel_id": "UCEhigSJQgvj9ADwYRYLkapA"
  },
  {
    "name": "Couch Investor",
    "handle": "CouchInvestor",
    "channel_id": "UC6ipRbtXU3-xJLET6oz6Hsw",
    "lang": "en"
  },
  {
    "name": "Chris Sain",
    "handle": "ChrisSain1",
    "channel_id": "UC5Bpgm3_pKxkhr0bz3X31Vw"
  },
  {
    "name": "Business with Brian",
    "handle": "BusinesswithBrian",
    "channel_id": "UCyqlbzLoYtpqDXwRI9Yh5LA"
  },
  {
    "name": "Asymmetric Investing",
    "handle": "AsymmetricInvesting",
    "channel_id": "UCM2udYo4m-_uQfbfLGwf6mA"
  },
  {
    "name": "Felix & Friends",
    "handle": "FelixFriends",
    "channel_id": "UCJtfma0mE_XrBAD9uakcjfA"
  },
  {
    "name": "Daniel Pronk",
    "handle": "DanielPronk",
    "channel_id": "UCL-F-8nxFtFZ4M3RWkGn6Qw"
  },
  {
    "name": "Parkev's Picks",
    "handle": "parkevtatevosiancfa9544",
    "channel_id": "UCwKB_00dPL3x5XmHF9IJCrg"
  },
  {
    "name": "Jerry Romine",
    "handle": "JerryRomineStocks",
    "channel_id": "UCMiJUXvEpHHW5JTnW-ez9EA"
  },
  {
    "name": "Ticker Symbol: YOU",
    "handle": "TickerSymbolYOU",
    "channel_id": "UCORX3Cl7ByidjEgzSCgv9Yw"
  },
  {
    "name": "The Patient Investor",
    "handle": "ThePatientInvestor",
    "channel_id": "UCAeAB8ABXGoGMbXuYPmiu2A"
  },
  {
    "name": "Stealth Wealth Investing",
    "handle": "StealthWealthInvesting",
    "channel_id": "UC3jzDUoiVCvr7hjCJurpsFg"
  },
  {
    "name": "Tom Nash",
    "handle": "TomNashTV",
    "channel_id": "UCJwKCyEIFHwUOPQQ-4kC1Zw"
  },
  {
    "name": "Adriconomics",
    "handle": "Adriconomics",
    "channel_id": "UCZuV88AJv5nDZDcY1UNGldQ"
  },
  {
    "name": "Antonio Linares",
    "handle": "alc_magic",
    "channel_id": "UChJdn-FOTmTc7nm-msFTqTQ"
  },
  {
    "name": "Rick Orford",
    "handle": "RickOrford",
    "channel_id": "UCC9CV2-VQpxtILJJ2RvPZCA"
  },
  {
    "name": "Wolf of Dubai",
    "handle": "wolfofdubai",
    "channel_id": "UCzBuoeqN94gdGcx5g4CgYNA"
  },
  {
    "name": "Christian Darnton - Investing",
    "handle": "ChristianDarnton1",
    "channel_id": "UCIU1WWwWzXfyYLz0cnjHv3A"
  }
]